radioscopy/__init__.py
radioscopy/radioscopy.py
radioscopy-0.1.dist-info/DESCRIPTION.rst
radioscopy-0.1.dist-info/METADATA
radioscopy-0.1.dist-info/RECORD
radioscopy-0.1.dist-info/WHEEL
radioscopy-0.1.dist-info/entry_points.txt
radioscopy-0.1.dist-info/metadata.json
radioscopy-0.1.dist-info/top_level.txt
radioscopy-0.1.dist-info/zip-safe
