Metadata-Version: 2.0
Name: radioscopy
Version: 0.1
Summary: Radio streaming player
Home-page: https://framagit.org/Steap/radioscopy
Author: Cyril Roelandt
Author-email: tipecaml@gmail.com
License: BSD
Keywords: radio
Platform: UNKNOWN
Classifier: License :: OSI Approved :: BSD License
Classifier: Programming Language :: Python :: 3
Classifier: Programming Language :: Python :: 3.5
Classifier: Programming Language :: Python :: 3.6
